easyflex/__init__.py
easyflex/api.py
easyflex/easyflex.py
easyflex/exceptions.py
easyflex/utils.py
easyflex-0.3.0.dist-info/LICENSE
easyflex-0.3.0.dist-info/METADATA
easyflex-0.3.0.dist-info/WHEEL
easyflex-0.3.0.dist-info/top_level.txt
easyflex-0.3.0.dist-info/RECORD
