Metadata-Version: 2.1
Name: easyflex
Version: 0.3.0
Summary: API connector voor het ontsluiten van data met de Easyflex API
Home-page: https://github.com/zypp-io/easyflex
Author: Zypp
Author-email: hello@zypp.io
Project-URL: Bug Tracker, https://github.com/zypp-io/easyflex/issues
Project-URL: Source, https://github.com/zypp-io/easyflex
Keywords: python,easyflex,API
Classifier: Programming Language :: Python :: 3
Classifier: License :: OSI Approved :: MIT License
Classifier: Operating System :: OS Independent
Requires-Python: >=3.8
License-File: LICENSE
Requires-Dist: pandas>=1.4.3
Requires-Dist: requests>=2.31.0
Requires-Dist: tqdm>=4.66.3
